{
	"name": "blobToSynapseDataflow",
	"properties": {
		"type": "MappingDataFlow",
		"typeProperties": {
			"sources": [
				{
					"dataset": {
						"referenceName": "sourceBlobDataset",
						"type": "DatasetReference"
					},
					"name": "sourceBlob"
				}
			],
			"sinks": [
				{
					"dataset": {
						"referenceName": "sinkSynapseDataset",
						"type": "DatasetReference"
					},
					"name": "sinkSynapse"
				}
			],
			"transformations": [],
			"script": "parameters{\n\tSchemaName as string\n}\nsource(allowSchemaDrift: true,\n\tvalidateSchema: false,\n\tignoreNoFilesFound: false,\n\tinferDriftedColumnTypes: true,\n\twildcardPaths:['taxi/yellow_tripdata_*-*.csv']) ~> sourceBlob\nsourceBlob sink(allowSchemaDrift: true,\n\tvalidateSchema: false,\n\tdeletable:false,\n\tinsertable:true,\n\tupdateable:false,\n\tupsertable:false,\n\tformat: 'table',\n\tstaged: true,\n\tallowCopyCommand: true,\n\tskipDuplicateMapInputs: true,\n\tskipDuplicateMapOutputs: true,\n\terrorHandlingOption: 'stopOnFirstError') ~> sinkSynapse"
		}
	}
}